{"topSpeed": [{"Driver": "ALB", "TopSpeed": 328, "Compound": "SOFT", "Team": "Red Bull Racing"}, {"Driver": "HUL", "TopSpeed": 328, "Compound": "SOFT", "Team": "Renault"}, {"Driver": "KVY", "TopSpeed": 328, "Compound": "SOFT", "Team": "Toro Rosso"}, {"Driver": "PER", "TopSpeed": 328, "Compound": "MEDIUM", "Team": "Racing Point"}, {"Driver": "STR", "TopSpeed": 326, "Compound": "SOFT", "Team": "Racing Point"}, {"Driver": "RIC", "TopSpeed": 326, "Compound": "SOFT", "Team": "Renault"}, {"Driver": "RUS", "TopSpeed": 325, "Compound": "SOFT", "Team": "Williams"}, {"Driver": "GIO", "TopSpeed": 325, "Compound": "SOFT", "Team": "Alfa Romeo Racing"}, {"Driver": "BOT", "TopSpeed": 324, "Compound": "MEDIUM", "Team": "Mercedes"}, {"Driver": "NOR", "TopSpeed": 324, "Compound": "SOFT", "Team": "McLaren"}, {"Driver": "VER", "TopSpeed": 323, "Compound": "MEDIUM", "Team": "Red Bull Racing"}, {"Driver": "GAS", "TopSpeed": 322, "Compound": "SOFT", "Team": "Toro Rosso"}, {"Driver": "LEC", "TopSpeed": 321, "Compound": "SOFT", "Team": "Ferrari"}, {"Driver": "SAI", "TopSpeed": 320, "Compound": "SOFT", "Team": "McLaren"}, {"Driver": "RAI", "TopSpeed": 320, "Compound": "SOFT", "Team": "Alfa Romeo Racing"}, {"Driver": "VET", "TopSpeed": 319, "Compound": "MEDIUM", "Team": "Ferrari"}, {"Driver": "HAM", "TopSpeed": 317, "Compound": "MEDIUM", "Team": "Mercedes"}, {"Driver": "GRO", "TopSpeed": 316, "Compound": "MEDIUM", "Team": "Haas F1 Team"}, {"Driver": "MAG", "TopSpeed": 313, "Compound": "SOFT", "Team": "Haas F1 Team"}, {"Driver": "KUB", "TopSpeed": 303, "Compound": "MEDIUM", "Team": "Williams"}]}