{"fastest": [{"Driver": "ALB", "LapTime": 76.142, "Diff": 0.0, "Team": "Red Bull Racing"}, {"Driver": "BOT", "LapTime": 76.693, "Diff": 0.551, "Team": "Mercedes"}, {"Driver": "VET", "LapTime": 77.041, "Diff": 0.899, "Team": "Ferrari"}, {"Driver": "LEC", "LapTime": 77.285, "Diff": 1.143, "Team": "Ferrari"}, {"Driver": "SAI", "LapTime": 77.786, "Diff": 1.644, "Team": "McLaren"}, {"Driver": "HUL", "LapTime": 77.899, "Diff": 1.757, "Team": "Renault"}, {"Driver": "RIC", "LapTime": 77.985, "Diff": 1.843, "Team": "Renault"}, {"Driver": "GAS", "LapTime": 78.1, "Diff": 1.958, "Team": "Toro Rosso"}, {"Driver": "KVY", "LapTime": 78.274, "Diff": 2.132, "Team": "Toro Rosso"}, {"Driver": "NOR", "LapTime": 78.559, "Diff": 2.417, "Team": "McLaren"}, {"Driver": "RUS", "LapTime": 78.779, "Diff": 2.637, "Team": "Williams"}, {"Driver": "MAG", "LapTime": 79.247, "Diff": 3.105, "Team": "Haas F1 Team"}, {"Driver": "STR", "LapTime": 79.414, "Diff": 3.272, "Team": "Racing Point"}, {"Driver": "RAI", "LapTime": 79.532, "Diff": 3.39, "Team": "Alfa Romeo Racing"}, {"Driver": "GIO", "LapTime": 79.6, "Diff": 3.458, "Team": "Alfa Romeo Racing"}, {"Driver": "LAT", "LapTime": 80.01, "Diff": 3.868, "Team": "Williams"}]}